{
  "criteriaSatisfied": [
    {
      "id": "useTower-tests",
      "status": "satisfied",
      "evidence": "useTower.test.ts exists at src/composables/__tests__/useTower.test.ts with 14 tests all passing"
    },
    {
      "id": "useChallengeTimer-tests",
      "status": "satisfied",
      "evidence": "useChallengeTimer.test.ts exists at src/composables/__tests__/useChallengeTimer.test.ts with 15 tests all passing"
    },
    {
      "id": "useChallengeStreak-tests",
      "status": "satisfied",
      "evidence": "useChallengeStreak.test.ts exists at src/composables/__tests__/useChallengeStreak.test.ts with 15 tests all passing"
    },
    {
      "id": "useNumberLineHop-tests",
      "status": "satisfied",
      "evidence": "useNumberLineHop.test.ts exists at src/composables/__tests__/useNumberLineHop.test.ts with 13 tests all passing"
    },
    {
      "id": "useBlocks-tests",
      "status": "satisfied",
      "evidence": "useBlocks.test.ts exists at src/composables/__tests__/useBlocks.test.ts with 27 tests all passing"
    },
    {
      "id": "useWaveRunner-tests",
      "status": "satisfied",
      "evidence": "useWaveRunner.test.ts exists at src/composables/__tests__/useWaveRunner.test.ts with 18 tests all passing"
    },
    {
      "id": "all-pass",
      "status": "satisfied",
      "evidence": "Runtime verification: 8 test files, 131 tests passed, 0 failed, exit code 0"
    }
  ],
  "changedFiles": [
    "D:/Documents/MathTrainer/src/composables/__tests__/useTower.test.ts",
    "D:/Documents/MathTrainer/src/composables/__tests__/useChallengeTimer.test.ts",
    "D:/Documents/MathTrainer/src/composables/__tests__/useChallengeStreak.test.ts",
    "D:/Documents/MathTrainer/src/composables/__tests__/useNumberLineHop.test.ts",
    "D:/Documents/MathTrainer/src/composables/__tests__/useBlocks.test.ts",
    "D:/Documents/MathTrainer/src/composables/__tests__/useWaveRunner.test.ts"
  ],
  "testsAddedOrUpdated": [
    "useTower.test.ts (14 tests)",
    "useChallengeTimer.test.ts (15 tests)",
    "useChallengeStreak.test.ts (15 tests)",
    "useNumberLineHop.test.ts (13 tests)",
    "useBlocks.test.ts (27 tests)",
    "useWaveRunner.test.ts (18 tests)"
  ],
  "commandsRun": [
    {
      "command": "cd D:/Documents/MathTrainer && npx vitest run src/composables/__tests__/",
      "result": "passed",
      "summary": "8 test files, 131 tests passed, 0 failed, exit code 0, duration 3.22s"
    }
  ],
  "validationOutput": [
    "6 new test files created covering all 6 gamification composables",
    "102 new unit tests added",
    "All 131 tests pass (102 new + 29 pre-existing)",
    "No regressions"
  ],
  "residualRisks": [
    "Vue warn on onUnmounted when testing composables outside component context - expected and harmless",
    "useNumberLineHop rAF-based animation not fully tested due to vi.useFakeTimers limitation"
  ],
  "noStagedFiles": true,
  "diffSummary": "Added 6 test files with 102 unit tests for all gamification composables: useTower, useChallengeTimer, useChallengeStreak, useNumberLineHop, useBlocks, useWaveRunner. All tests pass.",
  "reviewFindings": [],
  "manualNotes": "",
  "notes": "All 7 acceptance criteria satisfied. Verification command confirmed 8 files, 131 tests, 0 failures."
}
